{
  "lesson_metadata": {
    "title": "History ",
    "subject": "History",
    "topic": "Japanese Occupation",
    "level_grade": "Sec 2",
    "additional_instructions": "",
    "lesson_structure": {
      "num_sections": 3,
      "max_activities_per_section": 3
    },
    "generation_timestamp": "Tue Jun  3 14:38:26 +08 2025",
    "models_used": {
      "sections_model": "gpt-4o-mini-2024-07-18",
      "activities_model": "gpt-4o-mini-2024-07-18",
      "reasoning_enabled": false
    }
  },
  "generation_process": {
    "step_1_sections": {
      "reasoning_summary": "No reasoning - using gpt-4o-mini-2024-07-18 model",
      "generated_content": "**LESSON DESCRIPTION:**\nIn this lesson, students will explore the impact and significance of the Japanese Occupation in Singapore, examining its historical context, social implications, and the experiences of those who lived through it. Through engaging activities and discussions, students will develop a deeper understanding of how this period shaped Singapore's identity. Collaborative learning experiences will allow students to reflect on their knowledge and draw connections to present-day Singapore. By the end of the lesson, students will not only recall key events but also critically assess the effects of this transformative period in history. \n\n**RECOMMENDED KEY APPLICATIONS OF TECHNOLOGY (KAT):**\n1. Facilitate learning together - This KAT encourages collaboration among students, allowing them to share perspectives on the Japanese Occupation, thereby enhancing understanding through collective exploration.\n2. Develop metacognition - This KAT aids students in reflecting on their learning processes, allowing them to evaluate their thoughts and responses related to the topic, fostering deeper engagement with the history.\n\n**LESSON SECTIONS:**\n\n**Section 1: Introduction to the Japanese Occupation**\n- **Learning Objectives:** \n  - Identify and explain key events during the Japanese Occupation.\n  - Discuss the reasons behind Japan's invasion of Singapore.\n  - Analyze initial public reactions to the occupation.\n- **Description:** \n  This section sets the foundation for understanding the Japanese Occupation by outlining essential facts and events. Students will collaborate in small groups to gather and present information, developing a comprehensive view of the occupation’s onset.\n- **Teacher Notes:** \n  Facilitate group discussions, encourage questions, and guide students to ensure accurate understanding. Use multimedia resources to present diverse historical perspectives.\n- **KAT Connection:** \n  The inclusion of group collaboration aligns with the “Facilitate learning together” principle, promoting peer-to-peer learning and dialogue around the topic.\n\n**Section 2: Life Under Japanese Rule**\n- **Learning Objectives:** \n  - Evaluate the social, economic, and cultural impacts of Japanese rule on Singapore.\n  - Reflect on the experiences of various community segments during the occupation.\n  - Discuss resilience and resistance strategies employed by Singaporeans.\n- **Description:** \n  This section examines the day-to-day realities of life during the occupation. Through a combination of multimedia case studies and individual reflections, students will explore various aspects of life and resistance, enhancing empathy and critical thinking.\n- **Teacher Notes:** \n  Present case studies through video or narrative podcasts. Encourage students to engage with the materials critically. Structure discussions so students can share their insights and reflections.\n- **KAT Connection:** \n  The use of reflective activities supports the “Develop metacognition” KAT, enabling students to think critically about their responses and the broader implications of the social changes during the occupation.\n\n**Section 3: Legacy of the Japanese Occupation**\n- **Learning Objectives:** \n  - Assess the long-term effects of the Japanese Occupation on contemporary Singapore.\n  - Explore the narratives captured in national memory and education.\n  - Discuss how the occupation shaped Singapore’s path towards independence.\n- **Description:** \n  In this concluding section, students will analyze the legacy of the Japanese Occupation on modern Singapore. By researching different perspectives, they’ll link historical events to current national identity and resilience.\n- **Teacher Notes:** \n  Guide students through a research activity using digital tools and resources. Facilitate a class discussion to summarize the findings and encourage connections to current events.\n- **KAT Connection:** \n  This section fosters collaborative research, reinforcing the “Facilitate learning together” KAT by allowing students to share viewpoints and create a collective understanding of the occupation's legacy."
    },
    "step_2_activities": {
      "reasoning_summary": "No reasoning - using gpt-4o-mini-2024-07-18 model",
      "generated_content": "**SELECTED SLS TOOLS FOR THIS LESSON:**\n1. **Discussion Board**: This tool allows students to share their thoughts and insights openly, fostering a collaborative environment where multiple perspectives can be explored, which is critical in understanding historical contexts.\n2. **Embed YouTube Videos**: Engaging multimedia content enhances student engagement and helps visualize historical events, making learning more relatable and impactful.\n3. **Poll**: Quick polling can help gauge students' understanding and interest levels in certain topics, facilitating real-time feedback and enhancing discussions.\n4. **Rubrics**: The use of rubrics provides clear expectations for student contributions, particularly in group activities, ensuring that all students understand the assessment criteria for collaborative tasks.\n\n**RECOMMENDED KEY APPLICATIONS OF TECHNOLOGY (KAT):**\n1. **Facilitate learning together**: This principle is relevant as it encourages students to work collaboratively to form a deeper understanding of the Japanese Occupation through shared insights and group activities.\n2. **Develop metacognition**: By prompting students to reflect on their thoughts and learning processes, this KAT supports critical thinking and personal connection to the historical content, making it more meaningful.\n\n---\n\n**LESSON PLAN ACTIVITIES:**\n\n**Activity 1: Timeline Creation**\nSection: Introduction to the Japanese Occupation  \nInteraction Type: Student-Student  \nDuration: 15 minutes  \nLearning Objectives:  \n• Identify key events during the Japanese Occupation.  \n• Discuss the reasons behind Japan's invasion of Singapore.  \n\nInstructions:  \n1. In small groups, students will create a timeline of the key events of the Japanese Occupation using a shared Google Doc.  \n2. Each group is assigned specific events to research (e.g., the fall of Singapore, public reactions).  \n3. Students will present their timelines to the class, highlighting the significance of their assigned events.\n\nKAT Alignment:  \nThis activity promotes collaboration and dialogue among students, enhancing the understanding of the topic.\n\nSLS Tools:  \n- Discussion Board (for discussing timeline entries)  \n- Embed Google Docs (for timeline creation)  \n\nData Analysis:  \nMonitor engagement through the participation rate in group discussions and completion of timeline contributions.\n\nTeaching Notes:  \nEncourage students to ask questions during presentations and clarify any historical ambiguities.\n\n---\n\n**Activity 2: Multimedia Case Study Analysis**\nSection: Life Under Japanese Rule  \nInteraction Type: Student-Content  \nDuration: 20 minutes  \nLearning Objectives:  \n• Evaluate the social, economic, and cultural impacts of Japanese rule on Singapore.  \n• Reflect on the experiences of various community segments during the occupation.  \n\nInstructions:  \n1. Students will watch a short documentary from YouTube about daily life during the occupation.  \n2. After viewing, they will individually write a reflection on how life was impacted, focusing on one community segment (e.g., Chinese, Malay, Indian).  \n3. Share reflections in pairs and discuss similarities and differences in their perspectives.\n\nKAT Alignment:  \nThis activity fosters metacognition by encouraging students to reflect critically on their learning experiences.\n\nSLS Tools:  \n- Embed YouTube Videos (for documentary viewing)  \n- Discussion Board (for sharing reflections)  \n\nData Analysis:  \nTrack student engagement through the submission of individual reflections and participation in discussions.\n\nTeaching Notes:  \nPrepare to facilitate discussion and provide additional context for community experiences.\n\n---\n\n**Activity 3: Resilience and Resistance Strategies Presentation**\nSection: Life Under Japanese Rule  \nInteraction Type: Student-Student  \nDuration: 25 minutes  \nLearning Objectives:  \n• Discuss resilience and resistance strategies employed by Singaporeans.  \n• Analyze the social implications of these strategies.  \n\nInstructions:  \n1. Divide students into groups of 4. Each group researches a specific resistance strategy used during the occupation (e.g., underground movements, propaganda).  \n2. Using rubrics provided, groups will prepare a 5-minute presentation outlining their strategies, featuring an analysis of their effectiveness.  \n3. Peers will provide feedback using a structured format on the discussion board.\n\nKAT Alignment:  \nEncourages group collaboration and critical discussion, highlighting the importance of shared understanding.\n\nSLS Tools:  \n- Rubrics (for presentations)  \n- Discussion Board (for peer feedback)  \n\nData Analysis:  \nEvaluate the quality of presentations and peer feedback to gauge understanding and group dynamics.\n\nTeaching Notes:  \nGuide students on how to effectively present and provide constructive feedback to peers.\n\n---\n\n**Activity 4: Sharing Initial Reactions through Polls**\nSection: Introduction to the Japanese Occupation  \nInteraction Type: Student-Community  \nDuration: 10 minutes  \nLearning Objectives:  \n• Analyze initial public reactions to the occupation.  \n• Foster class discussion on historical perspectives.  \n\nInstructions:  \n1. Conduct a live poll to ask students how they think people reacted when the Japanese occupied Singapore (e.g., fear, anger, confusion).  \n2. After results are tallied, initiate a class discussion based on the results, prompting students to support their opinions with reasoning.  \n3. Use polls to gauge opinions on how different demographics may have reacted.\n\nKAT Alignment:  \nFacilitates collective learning by prompting discussion based on real-time data presented to the class.\n\nSLS Tools:  \n- Poll (for initial reactions)  \n\nData Analysis:  \nAssess the diversity of responses to understand varying perspectives among students.\n\nTeaching Notes:  \nDirect the discussion towards interpreting the implications of these reactions.\n\n---\n\n**Activity 5: Digital Journaling Reflection**\nSection: Life Under Japanese Rule  \nInteraction Type: Student-Content  \nDuration: 20 minutes  \nLearning Objectives:  \n• Reflect on personal insights regarding life under Japanese rule.  \n• Create awareness of historical experiences and their relevance today.  \n\nInstructions:  \n1. After engaging with multimedia resources on the impact of Japanese rule, students will write a digital journal entry capturing their personal reflections.  \n2. They will answer specific prompts (e.g., \"What would it have been like to live through this occupation?\").  \n3. Journal entries will be shared with the teacher for feedback on depth and insight.\n\nKAT Alignment:  \nSupports the development of metacognition through personal reflection about the historical content.\n\nSLS Tools:  \n- Embed Google Docs (for journaling)  \n\nData Analysis:  \nReview entries for thematic understanding and individual growth.\n\nTeaching Notes:  \nEncourage open expression while guiding students to connect their reflections with broader historical contexts.\n\n---\n\n**Activity 6: Legacy Research Collaborative Project**\nSection: Legacy of the Japanese Occupation  \nInteraction Type: Student-Student  \nDuration: 30 minutes  \nLearning Objectives:  \n• Assess the long-term effects of the Japanese Occupation on contemporary Singapore.  \n• Explore narratives captured in national memory.  \n\nInstructions:  \n1. Students will be divided into small groups and assigned specific aspects of Singaporean identity (e.g., education, national policies) that were influenced by the occupation.  \n2. Each group will research their topic using digital libraries and summarize their findings in a short presentation.  \n3. Presentations will culminate in a class discussion on the importance of historical narratives.\n\nKAT Alignment:  \nPromotes collaborative learning as students engage in research to support their analysis.\n\nSLS Tools:  \n- Embed Google Docs (for group research)  \n\nData Analysis:  \nEvaluate group presentations for understanding and clarity of the historical legacy.\n\nTeaching Notes:  \nProvide guidance on effective research techniques and focus on synthesizing their findings.\n\n---\n\n**Activity 7: Contemporary Connections Discussion**\nSection: Legacy of the Japanese Occupation  \nInteraction Type: Student-Community  \nDuration: 15 minutes  \nLearning Objectives:  \n• Discuss how the occupation shaped Singapore’s path towards independence.  \n• Analyze contemporary issues that may have roots in historical contexts.  \n\nInstructions:  \n1. Conduct a whole-class discussion on the impact of the Japanese Occupation on modern Singapore, using the discussion board as a space for students to comment.  \n2. Prompt students to consider contemporary events or policies and relate them to historical events from the occupation.  \n3. Students will actively engage by responding to their peers’ posts.\n\nKAT Alignment:  \nEncourages group discussion and reflection on the connections between past and present.\n\nSLS Tools:  \n- Discussion Board (for sharing modern connections)  \n\nData Analysis:  \nMonitor participation levels in the discussion to assess engagement with the topic.\n\nTeaching Notes:  \nEncourage critical thinking and ensure that multiple viewpoints are considered during the discussion.\n\n---\n\n**Activity 8: Critical Thinking Reflective Essay**\nSection: Legacy of the Japanese Occupation  \nInteraction Type: Student-Content  \nDuration: 25 minutes  \nLearning Objectives:  \n• Critically assess the effects of the Japanese Occupation on Singapore's identity.  \n• Articulate personal perspectives relating to historical narratives.  \n\nInstructions:  \n1. Students will write a reflective essay on the significance of the Japanese Occupation in shaping Singapore’s identity, guided by rubric-based criteria.  \n2. Essays should include personal insights and analysis based on both research and class discussions.  \n3. Submit essays for teacher feedback.\n\nKAT Alignment:  \nEncourages metacognitive reflection and critical assessment of historical narratives.\n\nSLS Tools:  \n- Rubrics (for assessment of essays)  \n\nData Analysis:  \nAssess the essays' depth and breadth of understanding based on rubric criteria.\n\nTeaching Notes:  \nFacilitate pre-writing workshops to help students organize their thoughts effectively.\n\n---\n\n**Activity 9: Historical Perspective Role-Play**\nSection: Life Under Japanese Rule  \nInteraction Type: Student-Student  \nDuration: 30 minutes  \nLearning Objectives:  \n• Analyze the experiences of different community segments during the occupation.  \n• Foster empathy and understanding of diverse historical perspectives.  \n\nInstructions:  \n1. In groups, students will role-play various community members during the occupation (e.g., local Chinese resident, Malay farmer, British expatriate).  \n2. Each group will create a short skit that portrays their character’s daily life and challenges.  \n3. Perform skits and then analyze the varying perspectives presented, discussing their impacts on social dynamics.\n\nKAT Alignment:  \nFosters collaborative learning as students engage creatively with historical contexts.\n\nSLS Tools:  \n- Discussion Board (for post-performance reflections)  \n\nData Analysis:  \nEvaluate participation and engagement in skits and discussions to monitor understanding.\n\nTeaching Notes:  \nEncourage creativity in skits while providing historical context and guidance for performance.",
      "structured_activities": {
        "selected_sls_tools": [
          "1. **Discussion Board**: This tool allows students to share their thoughts and insights openly, fostering a collaborative environment where multiple perspectives can be explored, which is critical in understanding historical contexts.",
          "2. **Embed YouTube Videos**: Engaging multimedia content enhances student engagement and helps visualize historical events, making learning more relatable and impactful.",
          "3. **Poll**: Quick polling can help gauge students' understanding and interest levels in certain topics, facilitating real-time feedback and enhancing discussions.",
          "4. **Rubrics**: The use of rubrics provides clear expectations for student contributions, particularly in group activities, ensuring that all students understand the assessment criteria for collaborative tasks."
        ],
        "recommended_kat": [
          "1. **Facilitate learning together**: This principle is relevant as it encourages students to work collaboratively to form a deeper understanding of the Japanese Occupation through shared insights and group activities.",
          "2. **Develop metacognition**: By prompting students to reflect on their thoughts and learning processes, this KAT supports critical thinking and personal connection to the historical content, making it more meaningful.",
          "---"
        ],
        "activities": [
          {
            "title": "Activity 1: Timeline Creation",
            "section": "Introduction to the Japanese Occupation",
            "interaction_type": "Student-Student",
            "duration": "15 minutes",
            "learning_objectives": [
              "Identify key events during the Japanese Occupation.",
              "Discuss the reasons behind Japan's invasion of Singapore."
            ],
            "instructions": "1. In small groups, students will create a timeline of the key events of the Japanese Occupation using a shared Google Doc.\n2. Each group is assigned specific events to research (e.g., the fall of Singapore, public reactions).\n3. Students will present their timelines to the class, highlighting the significance of their assigned events.",
            "kat_alignment": "This activity promotes collaboration and dialogue among students, enhancing the understanding of the topic.",
            "sls_tools": "- Discussion Board (for discussing timeline entries)\n- Embed Google Docs (for timeline creation)",
            "data_analysis": "Monitor engagement through the participation rate in group discussions and completion of timeline contributions.",
            "teaching_notes": "Encourage students to ask questions during presentations and clarify any historical ambiguities."
          },
          {
            "title": "Activity 2: Multimedia Case Study Analysis",
            "section": "Life Under Japanese Rule",
            "interaction_type": "Student-Content",
            "duration": "20 minutes",
            "learning_objectives": [
              "Evaluate the social, economic, and cultural impacts of Japanese rule on Singapore.",
              "Reflect on the experiences of various community segments during the occupation."
            ],
            "instructions": "1. Students will watch a short documentary from YouTube about daily life during the occupation.\n2. After viewing, they will individually write a reflection on how life was impacted, focusing on one community segment (e.g., Chinese, Malay, Indian).\n3. Share reflections in pairs and discuss similarities and differences in their perspectives.",
            "kat_alignment": "This activity fosters metacognition by encouraging students to reflect critically on their learning experiences.",
            "sls_tools": "- Embed YouTube Videos (for documentary viewing)\n- Discussion Board (for sharing reflections)",
            "data_analysis": "Track student engagement through the submission of individual reflections and participation in discussions.",
            "teaching_notes": "Prepare to facilitate discussion and provide additional context for community experiences."
          },
          {
            "title": "Activity 3: Resilience and Resistance Strategies Presentation",
            "section": "Life Under Japanese Rule",
            "interaction_type": "Student-Student",
            "duration": "25 minutes",
            "learning_objectives": [
              "Discuss resilience and resistance strategies employed by Singaporeans.",
              "Analyze the social implications of these strategies."
            ],
            "instructions": "1. Divide students into groups of 4. Each group researches a specific resistance strategy used during the occupation (e.g., underground movements, propaganda).\n2. Using rubrics provided, groups will prepare a 5-minute presentation outlining their strategies, featuring an analysis of their effectiveness.\n3. Peers will provide feedback using a structured format on the discussion board.",
            "kat_alignment": "Encourages group collaboration and critical discussion, highlighting the importance of shared understanding.",
            "sls_tools": "- Rubrics (for presentations)\n- Discussion Board (for peer feedback)",
            "data_analysis": "Evaluate the quality of presentations and peer feedback to gauge understanding and group dynamics.",
            "teaching_notes": "Guide students on how to effectively present and provide constructive feedback to peers."
          },
          {
            "title": "Activity 4: Sharing Initial Reactions through Polls",
            "section": "Introduction to the Japanese Occupation",
            "interaction_type": "Student-Community",
            "duration": "10 minutes",
            "learning_objectives": [
              "Analyze initial public reactions to the occupation.",
              "Foster class discussion on historical perspectives."
            ],
            "instructions": "1. Conduct a live poll to ask students how they think people reacted when the Japanese occupied Singapore (e.g., fear, anger, confusion).\n2. After results are tallied, initiate a class discussion based on the results, prompting students to support their opinions with reasoning.\n3. Use polls to gauge opinions on how different demographics may have reacted.",
            "kat_alignment": "Facilitates collective learning by prompting discussion based on real-time data presented to the class.",
            "sls_tools": "- Poll (for initial reactions)",
            "data_analysis": "Assess the diversity of responses to understand varying perspectives among students.",
            "teaching_notes": "Direct the discussion towards interpreting the implications of these reactions."
          },
          {
            "title": "Activity 5: Digital Journaling Reflection",
            "section": "Life Under Japanese Rule",
            "interaction_type": "Student-Content",
            "duration": "20 minutes",
            "learning_objectives": [
              "Reflect on personal insights regarding life under Japanese rule.",
              "Create awareness of historical experiences and their relevance today."
            ],
            "instructions": "1. After engaging with multimedia resources on the impact of Japanese rule, students will write a digital journal entry capturing their personal reflections.\n2. They will answer specific prompts (e.g., \"What would it have been like to live through this occupation?\").\n3. Journal entries will be shared with the teacher for feedback on depth and insight.",
            "kat_alignment": "Supports the development of metacognition through personal reflection about the historical content.",
            "sls_tools": "- Embed Google Docs (for journaling)",
            "data_analysis": "Review entries for thematic understanding and individual growth.",
            "teaching_notes": "Encourage open expression while guiding students to connect their reflections with broader historical contexts."
          },
          {
            "title": "Activity 6: Legacy Research Collaborative Project",
            "section": "Legacy of the Japanese Occupation",
            "interaction_type": "Student-Student",
            "duration": "30 minutes",
            "learning_objectives": [
              "Assess the long-term effects of the Japanese Occupation on contemporary Singapore.",
              "Explore narratives captured in national memory."
            ],
            "instructions": "1. Students will be divided into small groups and assigned specific aspects of Singaporean identity (e.g., education, national policies) that were influenced by the occupation.\n2. Each group will research their topic using digital libraries and summarize their findings in a short presentation.\n3. Presentations will culminate in a class discussion on the importance of historical narratives.",
            "kat_alignment": "Promotes collaborative learning as students engage in research to support their analysis.",
            "sls_tools": "- Embed Google Docs (for group research)",
            "data_analysis": "Evaluate group presentations for understanding and clarity of the historical legacy.",
            "teaching_notes": "Provide guidance on effective research techniques and focus on synthesizing their findings."
          },
          {
            "title": "Activity 7: Contemporary Connections Discussion",
            "section": "Legacy of the Japanese Occupation",
            "interaction_type": "Student-Community",
            "duration": "15 minutes",
            "learning_objectives": [
              "Discuss how the occupation shaped Singapore’s path towards independence.",
              "Analyze contemporary issues that may have roots in historical contexts."
            ],
            "instructions": "1. Conduct a whole-class discussion on the impact of the Japanese Occupation on modern Singapore, using the discussion board as a space for students to comment.\n2. Prompt students to consider contemporary events or policies and relate them to historical events from the occupation.\n3. Students will actively engage by responding to their peers’ posts.",
            "kat_alignment": "Encourages group discussion and reflection on the connections between past and present.",
            "sls_tools": "- Discussion Board (for sharing modern connections)",
            "data_analysis": "Monitor participation levels in the discussion to assess engagement with the topic.",
            "teaching_notes": "Encourage critical thinking and ensure that multiple viewpoints are considered during the discussion."
          },
          {
            "title": "Activity 8: Critical Thinking Reflective Essay",
            "section": "Legacy of the Japanese Occupation",
            "interaction_type": "Student-Content",
            "duration": "25 minutes",
            "learning_objectives": [
              "Critically assess the effects of the Japanese Occupation on Singapore's identity.",
              "Articulate personal perspectives relating to historical narratives."
            ],
            "instructions": "1. Students will write a reflective essay on the significance of the Japanese Occupation in shaping Singapore’s identity, guided by rubric-based criteria.\n2. Essays should include personal insights and analysis based on both research and class discussions.\n3. Submit essays for teacher feedback.",
            "kat_alignment": "Encourages metacognitive reflection and critical assessment of historical narratives.",
            "sls_tools": "- Rubrics (for assessment of essays)",
            "data_analysis": "Assess the essays' depth and breadth of understanding based on rubric criteria.",
            "teaching_notes": "Facilitate pre-writing workshops to help students organize their thoughts effectively."
          },
          {
            "title": "Activity 9: Historical Perspective Role-Play",
            "section": "Life Under Japanese Rule",
            "interaction_type": "Student-Student",
            "duration": "30 minutes",
            "learning_objectives": [
              "Analyze the experiences of different community segments during the occupation.",
              "Foster empathy and understanding of diverse historical perspectives."
            ],
            "instructions": "1. In groups, students will role-play various community members during the occupation (e.g., local Chinese resident, Malay farmer, British expatriate).\n2. Each group will create a short skit that portrays their character’s daily life and challenges.\n3. Perform skits and then analyze the varying perspectives presented, discussing their impacts on social dynamics.",
            "kat_alignment": "Fosters collaborative learning as students engage creatively with historical contexts.",
            "sls_tools": "- Discussion Board (for post-performance reflections)",
            "data_analysis": "Evaluate participation and engagement in skits and discussions to monitor understanding.",
            "teaching_notes": "Encourage creativity in skits while providing historical context and guidance for performance."
          }
        ]
      }
    }
  },
  "errors": {
    "activities_error": null
  }
}