{
  "lesson_metadata": {
    "title": "Rise and Fall of Japan",
    "subject": "History",
    "topic": "Japanese Occupation, Pearl Habour and Atomic Bombs",
    "level_grade": "Sec 3",
    "additional_instructions": "Embedd Scaffolding",
    "lesson_structure": {
      "num_sections": 3,
      "max_activities_per_section": 2
    },
    "generation_timestamp": "Tue Jun  3 14:41:27 +08 2025",
    "models_used": {
      "sections_model": "o4-mini",
      "activities_model": "o4-mini",
      "reasoning_enabled": true
    }
  },
  "generation_process": {
    "step_1_sections": {
      "reasoning_summary": "**Structuring educational sections**\n\nI don't need to list activities right now, so I'll focus on setting up the sections. I aim to reference the e-Pedagogy framework, active learning principles, and scaffolding, keeping the Singapore education context in mind. For KAT, I'll go with \"Embed scaffolding\" and \"Support assessment for learning.\" Embedding scaffolding is mandatory, so that’s a definite choice. I’ll also include support assessment for learning to gauge understanding through formative quizzes and facilitate collaborative discussions. I'll include brief explanations for both.",
      "generated_content": "LESSON DESCRIPTION:  \nIn this 50-minute module, Sec 3 students investigate the Rise and Fall of Japan through three focused explorations: the Japanese Occupation, the attack on Pearl Harbor, and the decision to drop the atomic bombs. Students will engage in scaffolded activities that build historical empathy, critical analysis, and ethical reasoning. Through multimedia sources, group discussions, and formative checks, learners will connect causes and consequences of wartime decisions. The lesson emphasises active learning and ongoing feedback to deepen understanding of complex events.  \n\nRECOMMENDED KEY APPLICATIONS OF TECHNOLOGY (KAT):  \n1. Embed scaffolding – Digital tools will guide students step-by-step through primary source analysis, ensuring structured support as they develop historical arguments.  \n2. Support assessment for learning – Interactive polls, quizzes and teacher feedback loops will provide real-time insights into student understanding, allowing targeted reteaching.  \n\nLESSON SECTIONS:  \n\nSection 1: Causes and Experiences of the Japanese Occupation  \n- Learning Objectives:  \n  • Identify the strategic motivations behind Japan’s expansion in Southeast Asia.  \n  • Describe lived experiences of occupied populations, with reference to Singapore.  \n  • Analyse how occupation policies affected daily life and local resistance.  \n- Description:  \n  Students begin by building foundational knowledge of why Japan expanded and how occupation policies were implemented. This sets the stage for understanding subsequent wartime decisions.  \n- Teacher Notes:  \n  • Activate prior knowledge by showing a brief video clip of life in pre-war Singapore.  \n  • Use an interactive timeline tool: learners drag events into order, with prompts if they err.  \n  • Facilitate small-group jigsaw: each group studies one aspect (economy, education, forced labour) and teaches peers.  \n- KAT Connection:  \n  Embed scaffolding through step-by-step analysis guides within the timeline tool; use quick polls to assess which occupation impacts require reteaching.  \n\nSection 2: Pearl Harbor – Strategic Surprise and Turning Points  \n- Learning Objectives:  \n  • Explain the strategic aims behind Japan’s attack on Pearl Harbor.  \n  • Evaluate the immediate military and diplomatic consequences of the attack.  \n  • Contrast Japanese and American perspectives using primary accounts.  \n- Description:  \n  This section shifts focus to a pivotal event that altered the course of World War II, promoting critical evaluation of source bias and consequence.  \n- Teacher Notes:  \n  • Provide structured source packets (scaffolded questions guide students through political speeches, diaries, propaganda posters).  \n  • Conduct a paired debate: one student argues Japan’s rationale, the other counters with U.S. strategic logic.  \n  • Use an embedded quiz after each source to check understanding and clarify misconceptions.  \n- KAT Connection:  \n  Support assessment for learning via instant quiz feedback; embed scaffolding with guided source-analysis prompts.  \n\nSection 3: The Atomic Bombs – Ethics, Impact, and Legacy  \n- Learning Objectives:  \n  • Describe the decision-making process leading to the bombing of Hiroshima and Nagasaki.  \n  • Assess the human, environmental and political consequences of atomic warfare.  \n  • Formulate and defend a reasoned position on the ethical use of atomic bombs.  \n- Description:  \n  In this capstone section, students grapple with moral dimensions and long-term fallout, synthesising knowledge from earlier sections.  \n- Teacher Notes:  \n  • Launch with a scaffolded graphic organiser contrasting pro- and anti-bomb arguments, citing eyewitness testimony and official documents.  \n  • Guide a fishbowl discussion: inner circle debates ethics while outer circle notes key points and asks probing questions.  \n  • Conclude with a reflective free-response prompt, using sentence starters to support lower-ability students.  \n- KAT Connection:  \n  Embed scaffolding through graphic organisers and sentence starters; support assessment for learning with rubric-based peer feedback during the fishbowl."
    },
    "step_2_activities": {
      "reasoning_summary": "**Planning lesson structure**\n\nI need to respond to the user’s request by selecting up to four unique SLS tools from the provided list. I’ll explain the rationale behind each tool to ensure clarity. Next, I’ll recommend two Key Applications of Technology (KAT) for integration. \n\nFor the lesson plan, I’ll outline six distinct activities with required details, ensuring I include learning objectives and specific instructions. Each activity will be clearly numbered and separated for ease of use. I'll keep my response free of hyperlinks or code snippets to meet guidelines.",
      "generated_content": "**SELECTED SLS TOOLS FOR THIS LESSON:**  \n1. Click and Drop Question – Enables students to sequence events (timeline ordering) with built-in feedback, reinforcing cause-effect relationships.  \n2. Progressive Quiz – Provides scaffolded, multi-part formative checks after source analysis, offering instant feedback and adaptive retry prompts.  \n3. Tooltip – Embeds in-context definitions, guiding questions and sentence starters directly within activities to support learners at point of need.  \n4. Embed Google Docs – Facilitates real-time collaborative research, jigsaw note-taking and peer feedback, tracking contributions via revision history.  \n\n**RECOMMENDED KEY APPLICATIONS OF TECHNOLOGY (KAT):**  \n1. Embed Scaffolding – Tooltip prompts, structured quiz items and document templates guide students step-by-step through complex analysis tasks.  \n2. Support Assessment for Learning – Analytics from Click and Drop and Progressive Quiz, together with revision histories in Google Docs, deliver real-time insight into student understanding for targeted reteaching.  \n\n**LESSON PLAN ACTIVITIES:**  \n\nActivity 1: Timeline Ordering Exercise  \nSection: Section 1 – Causes and Experiences of the Japanese Occupation  \nInteraction Type: Student-Content  \nDuration: 10 minutes  \nLearning Objectives:  \n• Identify the strategic motivations behind Japan’s expansion in Southeast Asia.  \n• Describe key events in the sequence of the Japanese occupation.  \n\nInstructions:  \n1. Open the Click and Drop timeline activity in SLS.  \n2. Read each event card; hover to reveal Tooltip definitions of key terms (e.g., “forced labour,” “strategic resource”).  \n3. Drag and drop the eight events into the correct chronological order.  \n4. If an event is misplaced, follow the on-screen prompt to review the Tooltip hint and try again.  \n5. Submit your final sequence.  \n\nKAT Alignment:  \n• Embed Scaffolding via Tooltip hints and step-by-step placement prompts.  \n• Support Assessment for Learning through instant feedback on sequence accuracy.  \n\nSLS Tools:  \nClick and Drop Question, Tooltip  \n\nData Analysis:  \n• Review Click and Drop analytics report to see common misplacements.  \n• Identify which events triggered the most hints for whole-class reteaching.  \n\nTeaching Notes:  \n• Circulate to observe which tooltips are most used.  \n• Highlight cause-effect links in class debrief, using the teacher dashboard to display aggregate results.  \n\n---  \n\nActivity 2: Jigsaw Research and Peer Teaching  \nSection: Section 1 – Causes and Experiences of the Japanese Occupation  \nInteraction Type: Student-Student  \nDuration: 20 minutes  \nLearning Objectives:  \n• Analyse how occupation policies (economy, education, forced labour) affected daily life.  \n• Explain local resistance strategies in Singapore under occupation.  \n\nInstructions:  \n1. Join your home group (3–4 students). Each member is assigned one aspect: economy, education or forced labour.  \n2. Open the shared Google Doc template. Use the pre-populated headings and Tooltip sentence starters (e.g., “One effect of forced labour was…”) to record your research.  \n3. Spend 8 minutes gathering key facts from the multimedia source links.  \n4. Form new expert groups (one specialist from each home group). In your expert group, take turns teaching your aspect using the Doc summary.  \n5. Return to your home group and teach peers what you learned.  \n\nKAT Alignment:  \n• Embed Scaffolding with Doc templates and Tooltip sentence starters.  \n• Support Assessment via revision history and peer comments for real-time insight.  \n\nSLS Tools:  \nEmbed Google Docs, Tooltip  \n\nData Analysis:  \n• Monitor Google Docs revision history to verify individual contributions.  \n• Collect peer-comment notes in the Doc for formative feedback.  \n\nTeaching Notes:  \n• Assign clear roles (recorder, presenter, questioner).  \n• Model use of sentence starters and encourage peers to ask clarifying questions.  \n\n---  \n\nActivity 3: Pearl Harbor Source Analysis Quiz  \nSection: Section 2 – Pearl Harbor – Strategic Surprise and Turning Points  \nInteraction Type: Student-Content  \nDuration: 15 minutes  \nLearning Objectives:  \n• Explain the strategic aims behind Japan’s attack on Pearl Harbor.  \n• Evaluate the immediate military and diplomatic consequences of the attack.  \n\nInstructions:  \n1. Access the three primary source excerpts in sequence within the Progressive Quiz.  \n2. For each excerpt:  \n   a. Read the source. Tooltips define challenging terms (e.g., “isolationism,” “fleet logistics”).  \n   b. Answer 2 multiple-choice questions and 1 short-answer question.  \n   c. Use the retry option if your score falls below 80%, guided by targeted feedback.  \n3. Proceed to the next source only after achieving 80% on the current set.  \n\nKAT Alignment:  \n• Embed Scaffolding via Tooltip definitions and tiered question prompts.  \n• Support Assessment through instant quiz analytics and mastery thresholds.  \n\nSLS Tools:  \nProgressive Quiz, Tooltip  \n\nData Analysis:  \n• Analyze question-level performance to pinpoint misconceptions.  \n• Track individual mastery and time-on-task per source.  \n\nTeaching Notes:  \n• Encourage use of “hint” feature before retrying.  \n• Debrief common errors and emphasize critical evaluation of bias.  \n\n---  \n\nActivity 4: Paired Debate Preparation  \nSection: Section 2 – Pearl Harbor – Strategic Surprise and Turning Points  \nInteraction Type: Student-Student  \nDuration: 15 minutes  \nLearning Objectives:  \n• Contrast Japanese and American perspectives using primary accounts.  \n• Articulate evidence-based arguments in a debate format.  \n\nInstructions:  \n1. Pair up; one student is “Pro-Japan rationale,” the other “Pro-USA defense.”  \n2. Open the shared Google Doc debate scaffold. Follow Tooltip prompts to draft:  \n   a. Three key arguments.  \n   b. Supporting evidence from the source quiz.  \n   c. A rebuttal sentence frame.  \n3. Each partner presents a 1-minute summary to another pair, swapping roles after feedback.  \n\nKAT Alignment:  \n• Embed Scaffolding with Doc prompts and sentence-frame Tooltips.  \n• Support Assessment through peer feedback noted in the Doc.  \n\nSLS Tools:  \nEmbed Google Docs, Tooltip  \n\nData Analysis:  \n• Review comment logs for depth of evidence use.  \n• Note time stamps for presentation pacing.  \n\nTeaching Notes:  \n• Model constructive rebuttal language.  \n• Circulate to prompt deeper analysis if arguments lack evidence.  \n\n---  \n\nActivity 5: Ethical Bombing Graphic Organizer  \nSection: Section 3 – The Atomic Bombs – Ethics, Impact, and Legacy  \nInteraction Type: Student-Content  \nDuration: 15 minutes  \nLearning Objectives:  \n• Describe the decision-making process leading to Hiroshima and Nagasaki bombings.  \n• Assess human and political consequences of atomic warfare.  \n\nInstructions:  \n1. Open the Google Doc graphic organizer with two columns: Pro-Bomb and Anti-Bomb.  \n2. Use Tooltip definitions of ethical terms (e.g., “just war theory,” “civilian immunity”).  \n3. Populate each column with three evidence points from readings/videos.  \n4. Highlight one point in each column you find most compelling.  \n\nKAT Alignment:  \n• Embed Scaffolding via structured organizer and in-situ Tooltips.  \n• Support Assessment for Learning through teacher review of submitted docs.  \n\nSLS Tools:  \nEmbed Google Docs, Tooltip  \n\nData Analysis:  \n• Examine organizer completeness and use of ethical terminology.  \n• Provide in-doc comments for targeted feedback.  \n\nTeaching Notes:  \n• Offer an exemplar entry.  \n• Encourage students to justify their highlighted points in annotations.  \n\n---  \n\nActivity 6: Fishbowl Debate and Reflection Quiz  \nSection: Section 3 – The Atomic Bombs – Ethics, Impact, and Legacy  \nInteraction Type: Student-Student  \nDuration: 20 minutes  \nLearning Objectives:  \n• Formulate and defend a reasoned position on the ethical use of atomic bombs.  \n• Reflect on how personal values influence historical interpretation.  \n\nInstructions:  \n1. Inner circle (4–5 students) debate for 8 minutes using arguments from their organizers. Outer circle observes and adds inline comments in a shared Google Doc (guided by Tooltip question prompts).  \n2. Swap roles: observers join the debate and vice versa for another 8 minutes.  \n3. Conclude with a 4-question Progressive Quiz self-reflection:  \n   a. Rate your confidence in your position.  \n   b. Identify one bias you recognized.  \n   c. Suggest one question for further study.  \n   d. Summarise a new insight.  \n\nKAT Alignment:  \n• Embed Scaffolding via Tooltip prompts during peer feedback.  \n• Support Assessment through peer comment logs and quiz reflection analytics.  \n\nSLS Tools:  \nEmbed Google Docs, Progressive Quiz, Tooltip  \n\nData Analysis:  \n• Review Progressive Quiz response distributions to assess self-awareness.  \n• Analyze Doc comments for depth and constructiveness of peer feedback.  \n\nTeaching Notes:  \n• Establish clear norms for respectful debate and feedback.  \n• Debrief by highlighting strong feedback examples and common reflection themes.",
      "structured_activities": {
        "selected_sls_tools": [
          "1. Click and Drop Question – Enables students to sequence events (timeline ordering) with built-in feedback, reinforcing cause-effect relationships.",
          "2. Progressive Quiz – Provides scaffolded, multi-part formative checks after source analysis, offering instant feedback and adaptive retry prompts.",
          "3. Tooltip – Embeds in-context definitions, guiding questions and sentence starters directly within activities to support learners at point of need.",
          "4. Embed Google Docs – Facilitates real-time collaborative research, jigsaw note-taking and peer feedback, tracking contributions via revision history."
        ],
        "recommended_kat": [
          "1. Embed Scaffolding – Tooltip prompts, structured quiz items and document templates guide students step-by-step through complex analysis tasks.",
          "2. Support Assessment for Learning – Analytics from Click and Drop and Progressive Quiz, together with revision histories in Google Docs, deliver real-time insight into student understanding for targeted reteaching."
        ],
        "activities": [
          {
            "title": "Activity 1: Timeline Ordering Exercise",
            "section": "Section 1 – Causes and Experiences of the Japanese Occupation",
            "interaction_type": "Student-Content",
            "duration": "10 minutes",
            "learning_objectives": [
              "Identify the strategic motivations behind Japan’s expansion in Southeast Asia.",
              "Describe key events in the sequence of the Japanese occupation."
            ],
            "instructions": "1. Open the Click and Drop timeline activity in SLS.\n2. Read each event card; hover to reveal Tooltip definitions of key terms (e.g., “forced labour,” “strategic resource”).\n3. Drag and drop the eight events into the correct chronological order.\n4. If an event is misplaced, follow the on-screen prompt to review the Tooltip hint and try again.\n5. Submit your final sequence.",
            "kat_alignment": "• Embed Scaffolding via Tooltip hints and step-by-step placement prompts.\n• Support Assessment for Learning through instant feedback on sequence accuracy.",
            "sls_tools": "Click and Drop Question, Tooltip",
            "data_analysis": "• Review Click and Drop analytics report to see common misplacements.\n• Identify which events triggered the most hints for whole-class reteaching.",
            "teaching_notes": "• Circulate to observe which tooltips are most used.\n• Highlight cause-effect links in class debrief, using the teacher dashboard to display aggregate results."
          },
          {
            "title": "Activity 2: Jigsaw Research and Peer Teaching",
            "section": "Section 1 – Causes and Experiences of the Japanese Occupation",
            "interaction_type": "Student-Student",
            "duration": "20 minutes",
            "learning_objectives": [
              "Analyse how occupation policies (economy, education, forced labour) affected daily life.",
              "Explain local resistance strategies in Singapore under occupation."
            ],
            "instructions": "1. Join your home group (3–4 students). Each member is assigned one aspect: economy, education or forced labour.\n2. Open the shared Google Doc template. Use the pre-populated headings and Tooltip sentence starters (e.g., “One effect of forced labour was…”) to record your research.\n3. Spend 8 minutes gathering key facts from the multimedia source links.\n4. Form new expert groups (one specialist from each home group). In your expert group, take turns teaching your aspect using the Doc summary.\n5. Return to your home group and teach peers what you learned.",
            "kat_alignment": "• Embed Scaffolding with Doc templates and Tooltip sentence starters.\n• Support Assessment via revision history and peer comments for real-time insight.",
            "sls_tools": "Embed Google Docs, Tooltip",
            "data_analysis": "• Monitor Google Docs revision history to verify individual contributions.\n• Collect peer-comment notes in the Doc for formative feedback.",
            "teaching_notes": "• Assign clear roles (recorder, presenter, questioner).\n• Model use of sentence starters and encourage peers to ask clarifying questions."
          },
          {
            "title": "Activity 3: Pearl Harbor Source Analysis Quiz",
            "section": "Section 2 – Pearl Harbor – Strategic Surprise and Turning Points",
            "interaction_type": "Student-Content",
            "duration": "15 minutes",
            "learning_objectives": [
              "Explain the strategic aims behind Japan’s attack on Pearl Harbor.",
              "Evaluate the immediate military and diplomatic consequences of the attack."
            ],
            "instructions": "1. Access the three primary source excerpts in sequence within the Progressive Quiz.\n2. For each excerpt:\na. Read the source. Tooltips define challenging terms (e.g., “isolationism,” “fleet logistics”).\nb. Answer 2 multiple-choice questions and 1 short-answer question.\nc. Use the retry option if your score falls below 80%, guided by targeted feedback.\n3. Proceed to the next source only after achieving 80% on the current set.",
            "kat_alignment": "• Embed Scaffolding via Tooltip definitions and tiered question prompts.\n• Support Assessment through instant quiz analytics and mastery thresholds.",
            "sls_tools": "Progressive Quiz, Tooltip",
            "data_analysis": "• Analyze question-level performance to pinpoint misconceptions.\n• Track individual mastery and time-on-task per source.",
            "teaching_notes": "• Encourage use of “hint” feature before retrying.\n• Debrief common errors and emphasize critical evaluation of bias."
          },
          {
            "title": "Activity 4: Paired Debate Preparation",
            "section": "Section 2 – Pearl Harbor – Strategic Surprise and Turning Points",
            "interaction_type": "Student-Student",
            "duration": "15 minutes",
            "learning_objectives": [
              "Contrast Japanese and American perspectives using primary accounts.",
              "Articulate evidence-based arguments in a debate format."
            ],
            "instructions": "1. Pair up; one student is “Pro-Japan rationale,” the other “Pro-USA defense.”\n2. Open the shared Google Doc debate scaffold. Follow Tooltip prompts to draft:\na. Three key arguments.\nb. Supporting evidence from the source quiz.\nc. A rebuttal sentence frame.\n3. Each partner presents a 1-minute summary to another pair, swapping roles after feedback.",
            "kat_alignment": "• Embed Scaffolding with Doc prompts and sentence-frame Tooltips.\n• Support Assessment through peer feedback noted in the Doc.",
            "sls_tools": "Embed Google Docs, Tooltip",
            "data_analysis": "• Review comment logs for depth of evidence use.\n• Note time stamps for presentation pacing.",
            "teaching_notes": "• Model constructive rebuttal language.\n• Circulate to prompt deeper analysis if arguments lack evidence."
          },
          {
            "title": "Activity 5: Ethical Bombing Graphic Organizer",
            "section": "Section 3 – The Atomic Bombs – Ethics, Impact, and Legacy",
            "interaction_type": "Student-Content",
            "duration": "15 minutes",
            "learning_objectives": [
              "Describe the decision-making process leading to Hiroshima and Nagasaki bombings.",
              "Assess human and political consequences of atomic warfare."
            ],
            "instructions": "1. Open the Google Doc graphic organizer with two columns: Pro-Bomb and Anti-Bomb.\n2. Use Tooltip definitions of ethical terms (e.g., “just war theory,” “civilian immunity”).\n3. Populate each column with three evidence points from readings/videos.\n4. Highlight one point in each column you find most compelling.",
            "kat_alignment": "• Embed Scaffolding via structured organizer and in-situ Tooltips.\n• Support Assessment for Learning through teacher review of submitted docs.",
            "sls_tools": "Embed Google Docs, Tooltip",
            "data_analysis": "• Examine organizer completeness and use of ethical terminology.\n• Provide in-doc comments for targeted feedback.",
            "teaching_notes": "• Offer an exemplar entry.\n• Encourage students to justify their highlighted points in annotations."
          },
          {
            "title": "Activity 6: Fishbowl Debate and Reflection Quiz",
            "section": "Section 3 – The Atomic Bombs – Ethics, Impact, and Legacy",
            "interaction_type": "Student-Student",
            "duration": "20 minutes",
            "learning_objectives": [
              "Formulate and defend a reasoned position on the ethical use of atomic bombs.",
              "Reflect on how personal values influence historical interpretation."
            ],
            "instructions": "1. Inner circle (4–5 students) debate for 8 minutes using arguments from their organizers. Outer circle observes and adds inline comments in a shared Google Doc (guided by Tooltip question prompts).\n2. Swap roles: observers join the debate and vice versa for another 8 minutes.\n3. Conclude with a 4-question Progressive Quiz self-reflection:\na. Rate your confidence in your position.\nb. Identify one bias you recognized.\nc. Suggest one question for further study.\nd. Summarise a new insight.",
            "kat_alignment": "• Embed Scaffolding via Tooltip prompts during peer feedback.\n• Support Assessment through peer comment logs and quiz reflection analytics.",
            "sls_tools": "Embed Google Docs, Progressive Quiz, Tooltip",
            "data_analysis": "• Review Progressive Quiz response distributions to assess self-awareness.\n• Analyze Doc comments for depth and constructiveness of peer feedback.",
            "teaching_notes": "• Establish clear norms for respectful debate and feedback.\n• Debrief by highlighting strong feedback examples and common reflection themes."
          }
        ]
      }
    }
  },
  "errors": {
    "activities_error": null
  }
}